{
  "cate": "5",
  "date": "6æ20æ¥ 5æ55å",
  "datetime": "2018-06-20T05:55",
  "video": "/news/html/20180620/movie/k10011486611_201806200548_201806200554.html",
  "duration": 73,
  "img": "html/20180620/K10011486611_1806200548_1806200555_01_03.jpg",
  "title": "京阪バス 自動運転の路線バスを実証実験へ",
  "summary": "運転手の不足が進む中、関西で大手のバス会社「京阪バス」が大津市の中心市街地で、路線バスの自動運転の実証実験を行うことになりました。事業化を前提に、街なかでバスの自動運転の実験が行われるのは珍しいということです。",
  "more": "実証実験は、大阪府など２府２県で路線バスを運行する関西で大手のバス会社「京阪バス」が大津市の協力を得て行います。<br /><br />来年度をめどにＪＲ大津駅からびわ湖までのおよそ１キロの大通りなど、大津市の中心市街地で自動運転のバスを運行する計画で、運転手が同乗し、客を乗せた営業運転ができるかどうかを検証します。<br /><br />国土交通省によりますと、民間のバス会社が事業化を前提に、街なかで自動運転の実験を行うのは全国でも珍しいということです。<br /><br />会社では実験で安全面や収益性などで問題がなければ、再来年をめどに運転手が同乗した自動運転で営業を始めることにしていて、運転手の不足が進む中、将来的には無人の自動運転を目指すとしています。<br /><br />京阪バスＩＣＴ推進部の大久保園明さんは「自動運転というツールを使うことで、収益を上げ、事業が持続可能となるモデルを作り上げたい」としています。",
  "body": [
    {
      "title": "",
      "img": "",
      "align": "",
      "text": "",
      "textPos": ""
    }
  ],
  "relationNews": [],
  "relationLink": [
    {
      "link": "http://www.nhk.or.jp/kaisetsu-blog/700/298602.html",
      "title": "「自動運転 地域はどう変わる？」（くらし☆解説）",
      "time": "解説委員室ブログ 5月31日",
      "datetime": "2018-05-31"
    },
    {
      "link": "//www3.nhk.or.jp/news/business_tokushu/2018_0525.html",
      "title": "潜入！ 中国 “自動運転シティー”",
      "time": "ビジネス特集 5月25日",
      "datetime": "2018-05-25"
    },
    {
      "link": "https://www3.nhk.or.jp/news/easy/k10011486611000/k10011486611000.html",
      "title": "京阪バス まちの中で自動運転のバスの実験をする計画",
      "time": "NEWSWEB EASY 6月21日",
      "datetime": "2018-06-21"
    }
  ],
  "word": [
    {
      "link": "word/0000009.html",
      "title": "IT・ネット"
    }
  ],
  "news_id": "k10011486611000",
  "yyyy": "2018",
  "mm": "06",
  "dd": "20",
  "url": "https://www3.nhk.or.jp/news/html/20180620/k10011486611000.html"
}