{
  "cate": "3",
  "date": "6æ16æ¥ 15æ30å",
  "datetime": "2018-06-16T15:30",
  "video": "",
  "duration": 0,
  "img": "html/20180616/K10011480841_1806161539_1806161540_01_02.jpg",
  "title": "ビートルズ来日公演の写真発見 貴重な最終公演の写真も",
  "summary": "1960年代に世界中を熱狂させたザ・ビートルズが、1966年、昭和41年に公演のために来日した際に撮影された、60点に上る写真が新たに見つかりました。このうち37点は、記録がほとんどないとされてきた最終日の公演を写したもので、鑑定した専門家は「資料的な価値が高く、新たな発見がないか研究のしがいがある」としています。",
  "more": "",
  "body": [
    {
      "title": "",
      "img": "html/20180616/K10011480841_1806161539_1806161540_01_03.jpg",
      "align": "",
      "text": "この写真は、1950年代から海外のジャズミュージシャンらを撮り続けた写真家で、10年前に亡くなった阿部克自さんの自宅の暗室で見つかりました。<br /><br />封筒の中に紙焼きの写真やフィルムがあり、音楽出版社と専門家が調べたところ、今から52年前、昭和41年のビートルズの来日公演の際に阿部さんが撮影した写真が60点、残されていたことがわかりました。<br /><br />写真は１点を除いてすべて未公開で、ビートルズの４人が６月29日に羽田空港に到着してホテルへ向かう場面や、日本武道館での公演の様子などが写されています。<br /><br />中でも、音源がなく、記録した写真も数点しかないとされてきた７月２日夜の最終公演が37点と半数以上を占め、大観衆に囲まれて演奏する４人の姿がさまざまなカットで撮影されていました。<br /><br />ビートルズの来日時の動向に詳しく、写真の鑑定にあたった大村亨さんは「もう出尽くしたと思われていたビートルズの資料が大量に出てきたこと自体、資料的な価値がものすごく高い。お客さんの熱狂や４人が気持ちよく演奏していることが伝わり、新たな発見がないか研究のしがいがある」としています。",
      "textPos": "top"
    },
    {
      "title": "ビートルズ 写真に写されていたのは",
      "img": "",
      "align": "",
      "text": "ビートルズの４人は、昭和41年６月29日に羽田空港に到着し、６月30日に１回、７月１日と２日にそれぞれ２回の合わせて５回、日本武道館で公演を行いました。<br /><br />公演には、合わせておよそ５万人が訪れ、全国的に熱狂的なファンを生んだほか、音楽やファッションが若者を中心に大きな影響を与えました。<br /><br />今回見つかった写真は、この時に写されたモノクロ56点、カラー４点で、このうちの37点は２日夜の最終公演の様子が写されていました。<br /><br />最終公演は、鑑賞した音楽評論家やファンの間で、当時の公演の中で演奏の完成度が最も高かったと伝えられていますが、音源はなく、写真も数点しかないとされてきました。<br /><br />今回の写真は、当時流行したサングラスをかけギターを抱えて歌うジョン・レノンをはじめ、マイクに向かってコーラスを加えるポール・マッカートニーとジョージ・ハリソン、それに一段高いステージでドラムを刻むリンゴ・スターが、スポットライトを浴びながら演奏する様子を、複数のレンズを巧みに使い分けながらはっきりととらえています。<br /><br />カメラの前に座っているファンの影が画面いっぱいに映り込んでいるものもあり、１万人近くが熱狂した伝説のコンサートの雰囲気を生々しく伝えています。<br /><br />また、羽田空港に到着した４人が、そろいのはっぴを着てタラップを降りる場面を写したモノクロの写真は、その後、メディアに配信され、現在もビートルズの来日を象徴する１枚となっていますが、今回の発見によって、阿部さんが撮影したことがわかりました。",
      "textPos": ""
    }
  ],
  "relationNews": [
    {
      "link": "html/20180616/k10011480851000.html",
      "title": "ビートルズ ジャズ専門の著名写真家が撮影保管",
      "date": "6月16日  15時46分",
      "datetime": "2018-06-16T15:46",
      "imgPath": "html/20180616/K10011480851_1806161600_1806161617_01_02.jpg",
      "iconPath": "html/20180616/K10011480851_1806161600_1806161617_02_01.jpg",
      "video": "",
      "duration": 0
    }
  ],
  "relationLink": [],
  "word": [
    {
      "link": "word/0000022.html",
      "title": "エンタメ"
    }
  ],
  "news_id": "k10011480841000",
  "yyyy": "2018",
  "mm": "06",
  "dd": "16",
  "url": "https://www3.nhk.or.jp/news/html/20180616/k10011480841000.html"
}